openadr3_client/__init__.py
openadr3_client/_auth/__init__.py
openadr3_client/_auth/token_manager.py
openadr3_client/_vtn/__init__.py
openadr3_client/_vtn/http/__init__.py
openadr3_client/_vtn/http/common/__init__.py
openadr3_client/_vtn/http/common/_authenticated_session.py
openadr3_client/_vtn/http/events.py
openadr3_client/_vtn/http/http_interface.py
openadr3_client/_vtn/http/programs.py
openadr3_client/_vtn/http/reports.py
openadr3_client/_vtn/http/subscriptions.py
openadr3_client/_vtn/http/vens.py
openadr3_client/_vtn/interfaces/__init__.py
openadr3_client/_vtn/interfaces/events.py
openadr3_client/_vtn/interfaces/filters.py
openadr3_client/_vtn/interfaces/programs.py
openadr3_client/_vtn/interfaces/reports.py
openadr3_client/_vtn/interfaces/subscriptions.py
openadr3_client/_vtn/interfaces/vens.py
openadr3_client/bl/__init__.py
openadr3_client/bl/_client.py
openadr3_client/bl/http_factory.py
openadr3_client/common/__init__.py
openadr3_client/common/_dict_helper.py
openadr3_client/conversion/__init__.py
openadr3_client/conversion/common/__init__.py
openadr3_client/conversion/common/dataframe.py
openadr3_client/conversion/common/dict.py
openadr3_client/conversion/input/__init__.py
openadr3_client/conversion/input/events/__init__.py
openadr3_client/conversion/input/events/_base_converter.py
openadr3_client/conversion/input/events/dict.py
openadr3_client/conversion/input/events/pandas.py
openadr3_client/conversion/output/__init__.py
openadr3_client/conversion/output/_base_converter.py
openadr3_client/conversion/output/events/__init__.py
openadr3_client/conversion/output/events/dict.py
openadr3_client/conversion/output/events/pandas.py
openadr3_client/logging.py
openadr3_client/models/__init__.py
openadr3_client/models/_base_model.py
openadr3_client/models/common/__init__.py
openadr3_client/models/common/attribute.py
openadr3_client/models/common/creation_guarded.py
openadr3_client/models/common/interval.py
openadr3_client/models/common/interval_period.py
openadr3_client-1.0.0.dist-info/METADATA
openadr3_client-1.0.0.dist-info/WHEEL
openadr3_client-1.0.0.dist-info/licenses/LICENSE.md
openadr3_client-1.0.0.dist-info/RECORD
