Metadata-Version: 2.4
Name: openadr3-client
Version: 1.0.0
Summary: 
License-Expression: Apache-2.0
License-File: LICENSE.md
Author: Nick van der Burgt
Author-email: nick.van.der.burgt@elaad.nl
Requires-Python: >=3.12, <4
Classifier: Programming Language :: Python :: 3
Classifier: Programming Language :: Python :: 3.12
Classifier: Programming Language :: Python :: 3.13
Classifier: Programming Language :: Python :: 3.14
Provides-Extra: pandas
Requires-Dist: oauthlib[signedtoken] (>=3.2.2,<4.0.0)
Requires-Dist: pandas (>=2.2.3,<3.0.0) ; extra == "pandas"
Requires-Dist: pandas-stubs (>=2.2.3.250308,<3.0.0.0) ; extra == "pandas"
Requires-Dist: pandera[mypy,pandas] (>=0.26.1,<0.27.0) ; extra == "pandas"
Requires-Dist: pycountry (>=24.6.1,<25.0.0)
Requires-Dist: pydantic (>=2.11.2,<3.0.0)
Requires-Dist: pydantic-extra-types (>=2.10.3,<3.0.0)
Requires-Dist: requests (>=2.32.3,<3.0.0)
Requires-Dist: requests-oauthlib (>=2.0.0,<3.0.0)
Project-URL: Bug Tracker, https://github.com/ElaadNL/openadr3-client/issues
Project-URL: Changelog, https://github.com/ElaadNL/openadr3-client/releases
Project-URL: Homepage, https://github.com/ElaadNL/openadr3-client
Project-URL: Repository, https://github.com/ElaadNL/openadr3-client
